katia/__init__.py
katia/interpreter/__init__.py
katia/interpreter/interpreter.py
katia/katia.py
katia/logger_manager/__init__.py
katia/logger_manager/log_config.yaml
katia/logger_manager/logger.py
katia/message_manager/__init__.py
katia/message_manager/consumer.py
katia/message_manager/producer.py
katia/owner.py
katia/recognizer/__init__.py
katia/recognizer/recognizer.py
katia/speaker/__init__.py
katia/speaker/speaker.py
katia-0.1.1.dist-info/WHEEL
katia-0.1.1.dist-info/METADATA
katia-0.1.1.dist-info/RECORD
